udsync/__init__.py
udsync/__main__.py
udsync/about.py
udsync/clipboard.py
udsync/human_bytes.py
udsync/lsblk.py
udsync/main.py
udsync/mime.py
udsync/model.py
udsync/py.typed
udsync/runmodule.sh
udsync/symlink.py
udsync/sync.py
udsync/ui.py
udsync/urwid_colors.py
udsync/urwid_dialog.py
udsync/urwid_directory_chooser.py
udsync/urwid_multi_key_support.py
udsync/doc/config.md
udsync-0.3.3.dist-info/entry_points.txt
udsync-0.3.3.dist-info/LICENSE
udsync-0.3.3.dist-info/WHEEL
udsync-0.3.3.dist-info/METADATA
udsync-0.3.3.dist-info/RECORD
