Metadata-Version: 2.1
Name: udsync
Version: 0.3.3
Summary: An interactive urwid based directory synchronizer
Author-email: erzo <erzo@posteo.de>
Requires-Python: >=3.7
Classifier: Operating System :: POSIX
Classifier: Operating System :: Unix
Classifier: Environment :: Console
Classifier: License :: OSI Approved :: BSD License
Requires-Dist: urwid
Requires-Dist: urwid-timed-progress
Requires-Dist: confattr >= 1.6.1, < 2.0.0
Requires-Dist: python-magic
Requires-Dist: tox ; extra == "test"
Project-URL: Home, https://gitlab.com/erzo/udsync
Provides-Extra: test
